ol_gpt/__init__.py
ol_gpt-0.0.6.dist-info/LICENSE
ol_gpt-0.0.6.dist-info/METADATA
ol_gpt-0.0.6.dist-info/WHEEL
ol_gpt-0.0.6.dist-info/entry_points.txt
ol_gpt-0.0.6.dist-info/top_level.txt
ol_gpt-0.0.6.dist-info/RECORD
